code2prompt/__init__.py
code2prompt/comment_stripper.py
code2prompt/language_inference.py
code2prompt/main.py
patched_code2prompt-0.2.0.dist-info/METADATA
patched_code2prompt-0.2.0.dist-info/WHEEL
patched_code2prompt-0.2.0.dist-info/entry_points.txt
patched_code2prompt-0.2.0.dist-info/RECORD
