Metadata-Version: 2.1
Name: patched-code2prompt
Version: 0.2.0
Summary: 
Author: Raphael MANSUY
Author-email: raphael.mansuy@gmail.com
Requires-Python: >=3.8,<4.0
Classifier: Programming Language :: Python :: 3
Classifier: Programming Language :: Python :: 3.8
Classifier: Programming Language :: Python :: 3.9
Classifier: Programming Language :: Python :: 3.10
Classifier: Programming Language :: Python :: 3.11
Requires-Dist: click (>=8.1.7,<9.0.0)
Requires-Dist: rich (>=13.7.1,<14.0.0)
